setup.py
listdates/__init__.py
listdates.egg-info/PKG-INFO
listdates.egg-info/SOURCES.txt
listdates.egg-info/dependency_links.txt
listdates.egg-info/entry_points.txt
listdates.egg-info/top_level.txt