Metadata-Version: 1.0
Name: listdates
Version: 0.0.1
Summary: A tools that list all dates in the given range
Home-page: UNKNOWN
Author: guan ming
Author-email: i@guanming.me
License: UNKNOWN
Platform: UNKNOWN
